ferris/__init__.py
ferris/base.py
ferris/client.py
ferrispy-0.0.0.dist-info/LICENSE
ferrispy-0.0.0.dist-info/METADATA
ferrispy-0.0.0.dist-info/WHEEL
ferrispy-0.0.0.dist-info/top_level.txt
ferrispy-0.0.0.dist-info/RECORD
